bencoding/__init__.py
bencoding/core.py
bencoding/py.typed
bencoded-0.1.2.dist-info/METADATA
bencoded-0.1.2.dist-info/WHEEL
bencoded-0.1.2.dist-info/licenses/LICENSE
bencoded-0.1.2.dist-info/RECORD
