Metadata-Version: 2.4
Name: bencoded
Version: 0.1.2
Summary: Decode benocoded binary files.
Author-email: Maxwell Muoto <maxmuoto@gmail.com>
License: MIT License
License-File: LICENSE
Requires-Python: <3.14,>=3.9
